<?xml version='1.0' encoding='UTF-8'?>
<topology>
  <nodes>
      <node id="n1">
          <interfaces>
              <interface>
                  <ip>10.0.0.10</ip>
                  <port>10000</port>
              </interface>
          </interfaces>
      </node>
      <node id="n2">
          <interfaces>
              <interface>
                  <ip>10.0.0.1</ip>
                  <port>10000</port>
              </interface>
              <interface>
                  <ip>10.0.1.1</ip>
                  <port>10000</port>
              </interface>
              <interface>
                  <ip>10.0.4.2</ip>
                  <port>10000</port>
              </interface>
          </interfaces>
      </node>
      <node id="n3">
          <interfaces>
              <interface>
                  <ip>10.0.4.1</ip>
                  <port>10000</port>
              </interface>
              <interface>
                  <ip>10.0.3.2</ip>
                  <port>10000</port>
              </interface>
              <interface>
                  <ip>10.0.5.1</ip>
                  <port>10000</port>
              </interface>
          </interfaces>
      </node>
      <node id="n4">
          <interfaces>
              <interface>
                  <ip>10.0.1.2</ip>
                  <port>10000</port>
              </interface>
              <interface>
                  <ip>10.0.2.1</ip>
                  <port>10000</port>
              </interface>
              <interface>
                  <ip>10.0.3.1</ip>
                  <port>10000</port>
              </interface>
          </interfaces>
      </node>
      <node id="n6">
          <interfaces>
              <interface>
                  <ip>10.0.5.20</ip>
                  <port>10000</port>
              </interface>
          </interfaces>
      </node>
      <node id="n5">
          <interfaces>
              <interface>
                  <ip>10.0.2.20</ip>
                  <port>10000</port>
              </interface>
          </interfaces>
      </node>
  </nodes>
  <links>
        <link id="1-2">
            <from node="n1"/>
            <to node="n2"/>
        </link>
        <link id="2-3">
            <from node="n2"/>
            <to node="n3"/>
        </link>
        <link id="2-1">
          <from node="n2"/>
          <to node="n1"/>
        </link>
        <link id="2-5">
          <from node="n2"/>
          <to node="n5"/>
        </link>
        <link id="3-2">
          <from node="n3"/>
          <to node="n2"/>
        </link>
        <link id="3-5">
          <from node="n3"/>
          <to node="n5"/>
        </link>
        <link id="3-4">
          <from node="n3"/>
          <to node="n4"/>
        </link>
        <link id="4-7">
          <from node="n4"/>
          <to node="n7"/>
        </link>
        <link id="4-6">
          <from node="n4"/>
          <to node="n6"/>
        </link>
        <link id="4-3">
          <from node="n4"/>
          <to node="n3"/>
        </link>
        <link id="5-7">
          <from node="n5"/>
          <to node="n7"/>
        </link>
        <link id="5-4">
          <from node="n5"/>
          <to node="n4"/>
        </link>
        <link id="5-2">
          <from node="n5"/>
          <to node="n2"/>
        </link>
        <link id="6-4">
          <from node="n6"/>
          <to node="n4"/>
        </link> 
        <link id="7-4">
          <from node="n7"/>
          <to node="n4"/>
        </link>    
        <link id="7-5">
          <from node="n7"/>
          <to node="n5"/>
        </link>     
  </links>
</topology>